criterion/__init__.py
criterion-0.0.1a1.dist-info/licenses/LICENSE
criterion-0.0.1a1.dist-info/METADATA
criterion-0.0.1a1.dist-info/WHEEL
criterion-0.0.1a1.dist-info/top_level.txt
criterion-0.0.1a1.dist-info/RECORD
