Metadata-Version: 2.4
Name: criterion
Version: 0.0.1a1
Summary: A Python package for Criterion
Author-email: Criterion Team <criterion@criterion.org>
License: MIT
Project-URL: Homepage, https://github.com/hzacode/criterion
Project-URL: Bug Tracker, https://github.com/hzacode/criterion/issues
Classifier: Development Status :: 2 - Pre-Alpha
Classifier: Intended Audience :: Developers
Classifier: License :: OSI Approved :: MIT License
Classifier: Programming Language :: Python :: 3
Classifier: Programming Language :: Python :: 3.7
Classifier: Programming Language :: Python :: 3.8
Classifier: Programming Language :: Python :: 3.9
Classifier: Programming Language :: Python :: 3.10
Classifier: Programming Language :: Python :: 3.11
Requires-Python: >=3.7
License-File: LICENSE
Dynamic: license-file
